jazzmin/__init__.py
jazzmin/apps.py
jazzmin/compat.py
jazzmin/locale/bg/LC_MESSAGES/django.mo
jazzmin/locale/bg/LC_MESSAGES/django.po
jazzmin/locale/de/LC_MESSAGES/django.mo
jazzmin/locale/de/LC_MESSAGES/django.po
jazzmin/locale/es/LC_MESSAGES/django.mo
jazzmin/locale/es/LC_MESSAGES/django.po
jazzmin/locale/fr/LC_MESSAGES/django.mo
jazzmin/locale/fr/LC_MESSAGES/django.po
jazzmin/locale/hu/LC_MESSAGES/django.mo
jazzmin/locale/hu/LC_MESSAGES/django.po
jazzmin/locale/ru/LC_MESSAGES/django.mo
jazzmin/locale/ru/LC_MESSAGES/django.po
jazzmin/locale/zh_Hans/LC_MESSAGES/django.mo
jazzmin/locale/zh_Hans/LC_MESSAGES/django.po
jazzmin/locale/zh_Hant/LC_MESSAGES/django.mo
jazzmin/locale/zh_Hant/LC_MESSAGES/django.po
jazzmin/settings.py
jazzmin/static/admin/js/cancel.js
jazzmin/static/admin/js/popup_response.js
jazzmin/static/jazzmin/css/main.css
jazzmin/static/jazzmin/img/calendar-icons.svg
jazzmin/static/jazzmin/img/default-log.svg
jazzmin/static/jazzmin/img/default.jpg
jazzmin/static/jazzmin/img/icon-calendar.svg
jazzmin/static/jazzmin/img/icon-changelink.svg
jazzmin/static/jazzmin/img/selector-icons.svg
jazzmin/static/jazzmin/js/change_form.js
jazzmin/static/jazzmin/js/change_list.js
jazzmin/static/jazzmin/js/main.js
jazzmin/static/jazzmin/js/related-modal.js
jazzmin/static/jazzmin/js/ui-builder.js
jazzmin/static/jazzmin/plugins/bootstrap-show-modal/bootstrap-show-modal.min.js
jazzmin/static/vendor/adminlte/css/adminlte.min.css
jazzmin/static/vendor/adminlte/css/adminlte.min.css.map
jazzmin/static/vendor/adminlte/img/AdminLTELogo.png
jazzmin/static/vendor/adminlte/img/icons.png
jazzmin/static/vendor/adminlte/img/user2-160x160.jpg
jazzmin/static/vendor/adminlte/js/adminlte.min.js
jazzmin/static/vendor/adminlte/js/adminlte.min.js.map
jazzmin/static/vendor/bootstrap/js/bootstrap.min.js
jazzmin/static/vendor/bootstrap/js/bootstrap.min.js.map
jazzmin/static/vendor/bootswatch/cerulean/bootstrap.min.css
jazzmin/static/vendor/bootswatch/cosmo/bootstrap.min.css
skn_django_jazzmin-2.6.2.dist-info/LICENSE
skn_django_jazzmin-2.6.2.dist-info/METADATA
skn_django_jazzmin-2.6.2.dist-info/WHEEL
skn_django_jazzmin-2.6.2.dist-info/RECORD
